Metadata-Version: 2.1
Name: key-encryption-gui
Version: 1.0.2
Summary: A GUI for encrypting private keys
Home-page: https://github.com/dfkburnem/Key-Encryption-GUI
Author: burnem
Author-email: dfkburnem@gmail.com
Classifier: Programming Language :: Python :: 3
Classifier: License :: OSI Approved :: MIT License
Classifier: Operating System :: Microsoft :: Windows
Requires-Python: >=3.6,<4
License-File: LICENSE
